.gitignore
.readthedocs.yml
.rtd-environment.yml
LICENSE.rst
MANIFEST.in
Makefile
README.rst
black_text.png
coverage.xml
make.bat
pyproject.toml
setup.cfg
setup.py
tox.ini
workflow.png
.eggs/README.txt
.github/ISSUE_TEMPLATE/bpass.md
.github/ISSUE_TEMPLATE/bugs.md
.github/ISSUE_TEMPLATE/docs.md
.github/ISSUE_TEMPLATE/feature.md
.github/workflows/testing.yml
docs/.nojekyll
docs/AgeWizard.html
docs/AgeWizard.ipynb
docs/CMDs.html
docs/CMDs.ipynb
docs/HR_diagrams.html
docs/HR_diagrams.ipynb
docs/Spectra.html
docs/Spectra.ipynb
docs/Transient_rates.html
docs/Transient_rates.ipynb
docs/citation.html
docs/cmd.html
docs/constants.html
docs/genindex.html
docs/hrdiagrams.html
docs/index.html
docs/intro.html
docs/load.html
docs/manual.html
docs/objects.inv
docs/py-modindex.html
docs/quick_start.html
docs/search.html
docs/searchindex.js
docs/_images/AgeWizard_13_0.png
docs/_images/AgeWizard_15_0.png
docs/_images/AgeWizard_31_1.png
docs/_images/HRD_data.png
docs/_images/HR_diagrams_11_1.png
docs/_images/HR_diagrams_13_1.png
docs/_images/HR_diagrams_15_1.png
docs/_images/HR_diagrams_17_1.png
docs/_images/HR_diagrams_27_0.png
docs/_images/HR_diagrams_31_2.png
docs/_images/Spectra_10_1.png
docs/_images/Spectra_12_1.png
docs/_images/Spectra_15_1.png
docs/_images/Spectra_20_1.png
docs/_images/Spectra_26_1.png
docs/_images/Spectra_28_1.png
docs/_images/Spectra_33_1.png
docs/_images/Spectra_35_0.png
docs/_images/Spectra_39_0.png
docs/_images/Spectra_41_1.png
docs/_images/Transient_rates_15_1.png
docs/_sources/AgeWizard.ipynb.txt
docs/_sources/CMDs.ipynb.txt
docs/_sources/HR_diagrams.ipynb.txt
docs/_sources/Spectra.ipynb.txt
docs/_sources/Transient_rates.ipynb.txt
docs/_sources/citation.rst.txt
docs/_sources/index.rst.txt
docs/_sources/intro.rst.txt
docs/_sources/manual.rst.txt
docs/_sources/quick_start.rst.txt
docs/_static/basic.css
docs/_static/doctools.js
docs/_static/documentation_options.js
docs/_static/favicon.png
docs/_static/file.png
docs/_static/hoki_white.png
hoki.egg-info/PKG-INFO
hoki.egg-info/SOURCES.txt
hoki.egg-info/dependency_links.txt
hoki.egg-info/not-zip-safe
hoki.egg-info/requires.txt
hoki.egg-info/top_level.txt
